gbgd_distributions/Binomialdistribution.py
gbgd_distributions/Gaussiandistribution.py
gbgd_distributions/Generaldistribution.py
gbgd_distributions/__init__.py
gbgd_distributions-1.5.dist-info/DESCRIPTION.rst
gbgd_distributions-1.5.dist-info/METADATA
gbgd_distributions-1.5.dist-info/RECORD
gbgd_distributions-1.5.dist-info/WHEEL
gbgd_distributions-1.5.dist-info/metadata.json
gbgd_distributions-1.5.dist-info/top_level.txt
