Metadata-Version: 2.0
Name: gbgd-distributions
Version: 1.5
Summary: Gaussian and Binomial Distributions
Home-page: UNKNOWN
Author: Olaotan Oladapo
Author-email: horlight@gmail.com
License: UNKNOWN
Platform: UNKNOWN
